arcane/string.py
arcane_string-1.0.0.dist-info/WHEEL
arcane_string-1.0.0.dist-info/METADATA
arcane_string-1.0.0.dist-info/RECORD
