Metadata-Version: 2.1
Name: arcane-string
Version: 1.0.0
Summary: A package to edit strings
Author: Arcane
Author-email: product@arcane.run
Requires-Python: >=3.6,<4.0
Classifier: Programming Language :: Python :: 3
Classifier: Programming Language :: Python :: 3.6
Classifier: Programming Language :: Python :: 3.7
Classifier: Programming Language :: Python :: 3.8
Classifier: Programming Language :: Python :: 3.9
Classifier: Programming Language :: Python :: 3.10
